<?xml version="1.0" encoding="utf-8" standalone="no"?>
<root xmlns:android="http://schemas.android.com/apk/res/android">
<receiver android:directBootAware="false" android:enabled="true" android:exported="true" android:name="androidx.profileinstaller.ProfileInstallReceiver" android:permission="android.permission.DUMP">
            <intent-filter>
                <action android:name="androidx.profileinstaller.action.INSTALL_PROFILE"/>
            </intent-filter>
            <intent-filter>
                <action android:name="androidx.profileinstaller.action.SKIP_FILE"/>
            </intent-filter>
            <intent-filter>
                <action android:name="androidx.profileinstaller.action.SAVE_PROFILE"/>
            </intent-filter>
            <intent-filter>
                <action android:name="androidx.profileinstaller.action.BENCHMARK_OPERATION"/>
            </intent-filter>
        </receiver>
</root>
