{
    "session_start_time": "2026-01-03",
    "project": "project_z",
    "summary": "Enhancing DEX and ELF analysis capabilities with a focus on accurate parsing, unified 32/64-bit support, and detailed JSON reporting.",
    "work_items": [
        {
            "id": "DEX_PARSING_FIX",
            "component": "dex.c",
            "status": "completed",
            "description": "Corrected logic for encoded_class_data and code_item to ensure all methods in a DEX file are processed accurately."
        },
        {
            "id": "DEX_ANALYSIS_REFINEMENT",
            "component": "analyseDex.c",
            "status": "completed",
            "description": "Reduced false positives in DEX analysis rules using string comparison fixes and null checks. Implemented single-pass detection to avoid duplicates."
        },
        {
            "id": "JSON_REPORT_INFRA",
            "component": "report.h/c",
            "status": "completed",
            "description": "Implemented a flexible JSON reporting system. Added 'source_file' and 'evidence' fields to findings to provide forensic context."
        },
        {
            "id": "ELF_UNIFICATION",
            "component": "isofunc.c",
            "status": "completed",
            "description": "Refactored ELF analysis to support both 32-bit and 64-bit shared objects using a unified path (normalizing headers to 64-bit structures)."
        },
        {
            "id": "ELF_GLOBAL_AGGREGATION",
            "component": "isofunc.c",
            "status": "completed",
            "description": "Implemented global counters for unsafe function usage. Findings are now aggregated across all scanned .so files to reduce report noise."
        },
        {
            "id": "FLAGHASH_REPAIR",
            "component": "flaghash.c",
            "status": "completed",
            "description": "Fixed critical bugs in hash matching: memory leaks during DB loading, incorrect loop bounds using sizeof(pointer), and SHA-256 buffer/logic errors."
        },
        {
            "id": "MAIN_LIFECYCLE",
            "component": "main.c",
            "status": "updated",
            "description": "Integrated DEX and ELF report propagation. Added cleanup or post-processing triggers (execve delete.sh)."
        },
        {
            "id": "DOCUMENTATION",
            "component": "README.md",
            "status": "completed",
            "description": "Created comprehensive project documentation including installation guides, build instructions, and troubleshooting."
        }
    ],
    "recent_changes": [
        {
            "file": ".gitignore",
            "modification": "Added *.json to ignore list (excluding session_analysis.json)."
        },
        {
            "file": "README.md",
            "modification": "Initial creation of project documentation."
        },
        {
            "file": "main.c",
            "modification": "Added execve('delete.sh', NULL, NULL) at program exit."
        },
        {
            "file": ".gitignore",
            "modification": "Added .json pattern to exclude local report files from version control."
        },
        {
            "file": "flaghash.c",
            "modification": "Implemented db_loaded flag and global counters for actual hash counts."
        }
    ]
}